deadgargoyle/__init__.py
deadgargoyle/dig.py
deadgargoyle/models.py
deadgargoyle-0.1.0.dist-info/DESCRIPTION.rst
deadgargoyle-0.1.0.dist-info/METADATA
deadgargoyle-0.1.0.dist-info/metadata.json
deadgargoyle-0.1.0.dist-info/RECORD
deadgargoyle-0.1.0.dist-info/top_level.txt
deadgargoyle-0.1.0.dist-info/WHEEL
