Metadata-Version: 2.0
Name: deadgargoyle
Version: 0.1.0
Summary: Identifies Gargoyle switches that are no longer necessary
Home-page: https://github.com/pydanny/deadgargoyle
Author: Daniel Roy Greenfeld
Author-email: pydanny@gmail.com
License: BSD
Keywords: deadgargoyle
Platform: UNKNOWN
Classifier: Development Status :: 2 - Pre-Alpha
Classifier: Framework :: Django
Classifier: Intended Audience :: Developers
Classifier: License :: OSI Approved :: Apache Software License
Classifier: Natural Language :: English
Classifier: Programming Language :: Python :: 2
Classifier: Programming Language :: Python :: 2.6
Classifier: Programming Language :: Python :: 2.7
